transcribetools/__init__.py
transcribetools/commandline.py
transcribetools/model.py
transcribetools/transcribe_folder.py
transcribetools-0.6.0.dist-info/METADATA
transcribetools-0.6.0.dist-info/WHEEL
transcribetools-0.6.0.dist-info/entry_points.txt
transcribetools-0.6.0.dist-info/licenses/LICENSE
transcribetools-0.6.0.dist-info/licenses/LICENSE-2.0.txt
transcribetools-0.6.0.dist-info/RECORD
