Metadata-Version: 2.4
Name: TranscribeTools
Version: 0.6.0
Summary: Transcribe and/or translate all soundfiles in a folder using a *local* Whisper model
License-File: LICENSE
License-File: LICENSE-2.0.txt
Requires-Python: >=3.12
Requires-Dist: attrs>=24.2.0
Requires-Dist: certifi==2025.7.14
Requires-Dist: deepl>=1.21.1
Requires-Dist: docutils==0.22rc5
Requires-Dist: keyring>=25.6.0
Requires-Dist: openai-whisper>=20240930
Requires-Dist: openai>=1.59.4
Requires-Dist: pymsgbox>=1.0.9
Requires-Dist: result>=0.17.0
Requires-Dist: rich-click>=1.8.5
Requires-Dist: soundfile>=0.13.0
Requires-Dist: static-ffmpeg>=2.13
Requires-Dist: toml>=0.10.2
Requires-Dist: transformers>=4.49.0
